ocrtext/__init__.py
ocrtext/config.py
ocrtext/main.py
sourav_easyocr-0.3.5.dist-info/LICENSE
sourav_easyocr-0.3.5.dist-info/METADATA
sourav_easyocr-0.3.5.dist-info/WHEEL
sourav_easyocr-0.3.5.dist-info/top_level.txt
sourav_easyocr-0.3.5.dist-info/RECORD
