Metadata-Version: 2.1
Name: sourav-easyocr
Version: 0.3.5
Summary: Input Adaptor to verify file extension
Home-page: UNKNOWN
Author: Crossml
Author-email: sourav@crossml.com
License: MIT
Keywords: Input-adaptor,Adaptor,DataAdaptor
Platform: UNKNOWN
Requires-Python: >=3
Requires-Dist: easyocr
Requires-Dist: opencv-python (==4.5.5.64)
Requires-Dist: pdf2image
